opclib
