Metadata-Version: 2.1
Name: opclib
Version: 0.0.7
Summary: A wrapper library for Open Pixel Control.
Home-page: https://github.com/gcpreston/opclib
Author: Graham Preston
Author-email: graham.preston@gmail.com
License: UNKNOWN
Project-URL: Source, https://github.com/gcpreston/opclib
Platform: UNKNOWN
Classifier: Development Status :: 3 - Alpha
Classifier: License :: OSI Approved :: MIT License
Classifier: Programming Language :: Python :: 3
Classifier: Programming Language :: Python :: 3.7
